toga_gtk/__init__.py
toga_gtk/app.py
toga_gtk/colors.py
toga_gtk/command.py
toga_gtk/container.py
toga_gtk/dialogs.py
toga_gtk/factory.py
toga_gtk/fonts.py
toga_gtk/icons.py
toga_gtk/images.py
toga_gtk/keys.py
toga_gtk/paths.py
toga_gtk/screens.py
toga_gtk/statusicons.py
toga_gtk/window.py
toga_gtk/hardware/__init__.py
toga_gtk/hardware/location.py
toga_gtk/libs/__init__.py
toga_gtk/libs/fontconfig.py
toga_gtk/libs/gtk.py
toga_gtk/libs/styles.py
toga_gtk/libs/utils.py
toga_gtk/resources/toga.png
toga_gtk/widgets/__init__.py
toga_gtk/widgets/activityindicator.py
toga_gtk/widgets/base.py
toga_gtk/widgets/box.py
toga_gtk/widgets/button.py
toga_gtk/widgets/canvas.py
toga_gtk/widgets/detailedlist.py
toga_gtk/widgets/divider.py
toga_gtk/widgets/imageview.py
toga_gtk/widgets/label.py
toga_gtk/widgets/mapview.py
toga_gtk/widgets/multilinetextinput.py
toga_gtk/widgets/numberinput.py
toga_gtk/widgets/optioncontainer.py
toga_gtk/widgets/passwordinput.py
toga_gtk/widgets/progressbar.py
toga_gtk/widgets/scrollcontainer.py
toga_gtk/widgets/selection.py
toga_gtk/widgets/slider.py
toga_gtk/widgets/splitcontainer.py
toga_gtk/widgets/switch.py
toga_gtk/widgets/table.py
toga_gtk/widgets/textinput.py
toga_gtk/widgets/tree.py
toga_gtk/widgets/webview.py
toga_gtk-0.5.1.dist-info/licenses/LICENSE
toga_gtk-0.5.1.dist-info/METADATA
toga_gtk-0.5.1.dist-info/WHEEL
toga_gtk-0.5.1.dist-info/entry_points.txt
toga_gtk-0.5.1.dist-info/top_level.txt
toga_gtk-0.5.1.dist-info/RECORD
